qtp/__init__.py
qtp/backtest/__init__.py
qtp/backtest/multi_backtest.py
qtp/backtest/single_backtest.py
qtp/strategy/__init__.py
qtp/strategy/sign01.py
qtp/strategy/sign02.py
qtp/strategy/sign03.py
qtp/strategy/sign04.py
qtp/tools/__init__.py
qtp/tools/data.py
qtp/tools/hun_dropbox.py
qtp/tools/indicator.py
qtp/tools/pick_best_data.py
qtp/tools/preprocessing.py
qtp/tools/utils.py
qtp-0.3.0.dist-info/METADATA
qtp-0.3.0.dist-info/WHEEL
qtp-0.3.0.dist-info/top_level.txt
qtp-0.3.0.dist-info/RECORD
