Metadata-Version: 2.1
Name: qtp
Version: 0.3.0
Summary: Quant Trading Packages
Home-page: https://github.com/smarthun0106/qtp
Download-URL: https://github.com/smarthun0106/qtp/archive/master.zip
Author: Taehun Kim
Author-email: smarthun0106@gmail.com
License: UNKNOWN
Keywords: pypi deploy
Platform: UNKNOWN
Classifier: Programming Language :: Python :: 3
Classifier: Programming Language :: Python :: 3.2
Classifier: Programming Language :: Python :: 3.3
Classifier: Programming Language :: Python :: 3.4
Classifier: Programming Language :: Python :: 3.5
Classifier: Programming Language :: Python :: 3.6
Classifier: Programming Language :: Python :: 3.7
Requires-Python: >=3
Requires-Dist: numpy
Requires-Dist: pandas
Requires-Dist: dropbox
Requires-Dist: tqdm
Requires-Dist: scipy
